cmcp/__init__.py
cmcp/config.py
cmcp/main.py
cmcp/kb/__init__.py
cmcp/kb/document_store.py
cmcp/kb/models.py
cmcp/kb/path.py
cmcp/kb/search/__init__.py
cmcp/kb/search/graph.py
cmcp/kb/search/manager.py
cmcp/kb/search/recovery.py
cmcp/kb/search/reranker.py
cmcp/kb/search/service.py
cmcp/kb/search/sparse.py
cmcp/managers/__init__.py
cmcp/managers/bash_manager.py
cmcp/managers/file_manager.py
cmcp/managers/knowledge_base_manager.py
cmcp/managers/list_manager.py
cmcp/managers/market_manager.py
cmcp/managers/python_manager.py
cmcp/managers/rss_manager.py
cmcp/managers/web_manager.py
cmcp/tools/__init__.py
cmcp/tools/file.py
cmcp/tools/kb.py
cmcp/tools/list.py
cmcp/tools/market.py
cmcp/tools/rss.py
cmcp/tools/system.py
cmcp/tools/web.py
cmcp/types/file.py
cmcp/utils/__init__.py
cmcp/utils/diff.py
cmcp/utils/io.py
cmcp/utils/logging.py
iflow_mcp_54rt1n_container_mcp-0.0.1.dist-info/licenses/LICENSE
iflow_mcp_54rt1n_container_mcp-0.0.1.dist-info/METADATA
iflow_mcp_54rt1n_container_mcp-0.0.1.dist-info/WHEEL
iflow_mcp_54rt1n_container_mcp-0.0.1.dist-info/entry_points.txt
iflow_mcp_54rt1n_container_mcp-0.0.1.dist-info/top_level.txt
iflow_mcp_54rt1n_container_mcp-0.0.1.dist-info/RECORD
