Metadata-Version: 2.4
Name: iflow-mcp_54rt1n_container-mcp
Version: 0.0.1
Summary: Container-based MCP implementation for secure tool execution
Author-email: 54rt1n <opensource@bmds.us>
Requires-Python: >=3.12
License-File: LICENSE
Requires-Dist: mcp[cli]>=1.0.0
Requires-Dist: aiofiles>=0.8.0
Requires-Dist: asyncio>=3.4.3
Requires-Dist: aiohttp>=3.8.0
Requires-Dist: playwright>=1.31.0
Requires-Dist: beautifulsoup4>=4.11.1
Requires-Dist: pydantic>=2.0.0
Requires-Dist: pyyaml>=6.0
Requires-Dist: tantivy>=0.24.0
Requires-Dist: sentence-transformers>=4.0.1
Requires-Dist: psutil>=7.0.0
Requires-Dist: yfinance>=1.0
Requires-Dist: feedparser>=6.0.12
Provides-Extra: dev
Requires-Dist: pytest>=7.0.0; extra == "dev"
Requires-Dist: pytest-asyncio>=0.18.3; extra == "dev"
Requires-Dist: pytest-cov>=3.0.0; extra == "dev"
Requires-Dist: ruff>=0.0.245; extra == "dev"
Requires-Dist: black>=23.0.0; extra == "dev"
Requires-Dist: ipython>=8.10.0; extra == "dev"
Requires-Dist: pdbpp>=0.10.3; extra == "dev"
Dynamic: license-file
